moreorless/__init__.py
moreorless/click.py
moreorless/patch.py
moreorless/py.typed
moreorless/tests/__init__.py
moreorless/tests/__main__.py
moreorless/tests/click.py
moreorless/tests/general.py
moreorless/tests/patch.py
moreorless-0.4.0.dist-info/LICENSE
moreorless-0.4.0.dist-info/METADATA
moreorless-0.4.0.dist-info/WHEEL
moreorless-0.4.0.dist-info/top_level.txt
moreorless-0.4.0.dist-info/RECORD
