Metadata-Version: 2.1
Name: moreorless
Version: 0.4.0
Summary: Python diff wrapper
Home-page: https://github.com/thatch/moreorless/
Author: Tim Hatch
Author-email: tim@timhatch.com
License: MIT
Platform: UNKNOWN
Requires-Python: >=3.6
